{
        "response": [
                {
                        "maintainer": "MAdMiZ",
                        "oem": "Realme",
                        "device": "Realme 5 Series",
                        "filename": "Cherish-OS-v3.9.5-20220805-1712-r5x-OFFICIAL-GApps.zip",
                        "download": "https://sourceforge.net/projects/cherish-os/files/device/r5x/Cherish-OS-v3.9.5-20220805-1712-r5x-OFFICIAL-GApps.zip/download",
                        "timestamp": 1659701630,
                        "md5": "4004e0dc09a10e6da35a09f51109f526",
                        "sha256": "6e491d5101bdf1e8c0c8093e36be16e1b7bd5f47b0dbe1875f6b1668ad17434f",
                        "size": 1698857065,
                        "version": 3.9.5,
                        "buildtype": "Active Development Releases",
                        "forum": "https://t.me/cherishOS",
                        "firmware": "https://github.com/realme-trinket-organization/firmware_files_RMX1911/releases",
                        "modem": "",
                        "bootloader": "",
                        "recovery": "https://pitchblackrecovery.com/r5x",
                        "paypal": "https://www.paypal.me/hungphan2001",
                        "telegram": "https://t.me/HOME_MAdMiZ,
                        "dt": "https://github.com/CherishOS-Devices/device_realme_r5x",
                        "common-dt": "https://github.com/CherishOS-Devices/vendor_realme_r5x",
                        "kernel": "https://codeberg.org/mizdrake7/kernel_realme_r5x"
                }
        ]
}
