{
	"response": [
		{
			"maintainer": "Perses",
			"oem": "Realme",
			"device": "Realme X3",
			"filename": "Cherish-OS-v4.12-20231003-0316-x3-OFFICIAL-GApps.zip",
			"download": "https://sourceforge.net/projects/cherish-os/files/device/x3/Cherish-OS-v4.12-20231003-0316-x3-OFFICIAL-GApps.zip/download",
			"timestamp": 1696302803,
			"md5": "8febae2ccd6721b7504042448734b222",
			"sha256": "85b28a3c27e0d9a66bc06e457cd2d4332bf1837c6338053f7198635ea56fa200",
			"size": 1496701048,
			"version": 4.12,
			"buildtype": "Active Development Releases",
			"forum": "",
                        "gapps": "",
			"firmware": "",
			"modem": "",
			"bootloader": "",
			"recovery": "https://t.me/RealmeX3Updates/112",
			"paypal": "https://www.paypal.me/hungphan2001",
			"telegram": "https://t.me/persesupdate",
			"dt": "",
			"common-dt": "",
			"kernel": ""
		}
	]
}

